<?xml version="1.0" encoding="UTF-8"?>
<MetaDataObject xmlns="http://v8.1c.ru/8.3/MDClasses" xmlns:app="http://v8.1c.ru/8.2/managed-application/core" xmlns:cfg="http://v8.1c.ru/8.1/data/enterprise/current-config" xmlns:cmi="http://v8.1c.ru/8.2/managed-application/cmi" xmlns:ent="http://v8.1c.ru/8.1/data/enterprise" xmlns:lf="http://v8.1c.ru/8.2/managed-application/logform" xmlns:style="http://v8.1c.ru/8.1/data/ui/style" xmlns:sys="http://v8.1c.ru/8.1/data/ui/fonts/system" xmlns:v8="http://v8.1c.ru/8.1/data/core" xmlns:v8ui="http://v8.1c.ru/8.1/data/ui" xmlns:web="http://v8.1c.ru/8.1/data/ui/colors/web" xmlns:win="http://v8.1c.ru/8.1/data/ui/colors/windows" xmlns:xen="http://v8.1c.ru/8.3/xcf/enums" xmlns:xpr="http://v8.1c.ru/8.3/xcf/predef" xmlns:xr="http://v8.1c.ru/8.3/xcf/readable" xmlns:xs="http://www.w3.org/2001/XMLSchema" xmlns:xsi="http://www.w3.org/2001/XMLSchema-instance" version="2.19">
	<DocumentJournal uuid="9bdef8a6-ffb2-4875-82fd-47c553a8281d">
		<InternalInfo>
			<xr:GeneratedType name="DocumentJournalSelection.PurchasesAndSales" category="Selection">
				<xr:TypeId>96055c62-929d-4195-a35b-cdd58dff24c8</xr:TypeId>
				<xr:ValueId>9e1e37fb-d3cf-40da-acea-79230fa2e169</xr:ValueId>
			</xr:GeneratedType>
			<xr:GeneratedType name="DocumentJournalList.PurchasesAndSales" category="List">
				<xr:TypeId>6ec42724-bc1f-430b-a4a6-e17087e47c45</xr:TypeId>
				<xr:ValueId>d55c5da8-4e9e-4e11-be1d-288b6d7053c7</xr:ValueId>
			</xr:GeneratedType>
			<xr:GeneratedType name="DocumentJournalManager.PurchasesAndSales" category="Manager">
				<xr:TypeId>e5411414-6f01-41f3-a456-20ae1ca96507</xr:TypeId>
				<xr:ValueId>a0352beb-e866-4d9c-9f24-26e49947751a</xr:ValueId>
			</xr:GeneratedType>
		</InternalInfo>
		<Properties>
			<Name>PurchasesAndSales</Name>
			<Synonym>
				<v8:item>
					<v8:lang>en</v8:lang>
					<v8:content>Purchases and sales</v8:content>
				</v8:item>
			</Synonym>
			<Comment/>
			<DefaultForm/>
			<AuxiliaryForm/>
			<UseStandardCommands>true</UseStandardCommands>
			<RegisteredDocuments>
				<xr:Item xsi:type="xr:MDObjectRef">Document.PurchaseInvoice</xr:Item>
				<xr:Item xsi:type="xr:MDObjectRef">Document.SalesInvoice</xr:Item>
				<xr:Item xsi:type="xr:MDObjectRef">Document.ReturnOfGoodsFromCustomer</xr:Item>
			</RegisteredDocuments>
			<IncludeHelpInContents>false</IncludeHelpInContents>
			<ListPresentation/>
			<ExtendedListPresentation/>
			<Explanation/>
		</Properties>
		<ChildObjects>
			<Column uuid="9e21df68-5159-44ae-af51-4b0ea57516fe">
				<Properties>
					<Name>Counterparty</Name>
					<Synonym>
						<v8:item>
							<v8:lang>en</v8:lang>
							<v8:content>Counterparty</v8:content>
						</v8:item>
					</Synonym>
					<Comment/>
					<Indexing>DontIndex</Indexing>
					<References>
						<xr:Item xsi:type="xr:MDObjectRef">Document.PurchaseInvoice.Attribute.Vendor</xr:Item>
						<xr:Item xsi:type="xr:MDObjectRef">Document.SalesInvoice.Attribute.Customer</xr:Item>
						<xr:Item xsi:type="xr:MDObjectRef">Document.ReturnOfGoodsFromCustomer.Attribute.Customer</xr:Item>
					</References>
				</Properties>
			</Column>
		</ChildObjects>
	</DocumentJournal>
</MetaDataObject>